juiz/__init__.py
juiz/__main__.py
juiz/decorators.py
juiz/juiz.py
juiz/proxy/__init__.py
pyjuiz-0.0.4.dist-info/METADATA
pyjuiz-0.0.4.dist-info/WHEEL
pyjuiz-0.0.4.dist-info/top_level.txt
pyjuiz-0.0.4.dist-info/RECORD
