Metadata-Version: 2.4
Name: pyjuiz
Version: 0.0.4
Summary: Python binding interface for JUIZ robot middleware components
Home-page: https://github.com/juiz
Author: ysuga
Author-email: ysuga@ysuga.net
License: MIT
Keywords: robot,middleware
Classifier: Programming Language :: Python :: 3.10
Requires-Dist: pyyaml
Requires-Dist: httpx
Requires-Dist: pillow
Dynamic: author
Dynamic: author-email
Dynamic: classifier
Dynamic: home-page
Dynamic: keywords
Dynamic: license
Dynamic: requires-dist
Dynamic: summary
